pttavm/__init__.py
pttavm/client.py
pttavm/models/category.py
pttavm/models/product.py
pttavm/models/stock.py
pttavm/services/base_service.py
pttavm/services/category_service.py
pttavm/services/product_service.py
pttavm/services/stock_service.py
pttavm/services/version_service.py
pttavm/utils/archiver.py
pttavm/utils/version.py
pttavm-0.1.3.dist-info/METADATA
pttavm-0.1.3.dist-info/WHEEL
pttavm-0.1.3.dist-info/top_level.txt
pttavm-0.1.3.dist-info/RECORD
