Metadata-Version: 2.1
Name: pttavm
Version: 0.1.3
Summary: A client for interacting with PTT AVM API
Author-email: Selim Kosgen <selimkosgen1999@gmail.com>
Classifier: Programming Language :: Python :: 3
Classifier: License :: OSI Approved :: MIT License
Classifier: Operating System :: OS Independent
Requires-Python: >=3.7
Requires-Dist: requests
Requires-Dist: xmltodict
Requires-Dist: python-dateutil
Requires-Dist: python-dotenv
Provides-Extra: dev
Requires-Dist: pytest>=6.0; extra == "dev"
Requires-Dist: pytest-cov; extra == "dev"
Requires-Dist: black; extra == "dev"
Requires-Dist: isort; extra == "dev"
Requires-Dist: flake8; extra == "dev"
